VTUResults-2.0.1.dist-info/top_level.txt
VTUResults-2.0.1.dist-info/metadata.json
VTUResults-2.0.1.dist-info/WHEEL
VTUResults-2.0.1.dist-info/METADATA
VTUResults-2.0.1.dist-info/RECORD
VTUResults-2.0.1.dist-info/DESCRIPTION.rst
vr/__init__.py
vr/constants.py
vr/vr.py
vr/utils.py
