Metadata-Version: 2.0
Name: VTUResults
Version: 2.0.1
Summary: Python Package for accessing VTU Results.
Home-page: https://github.com/maheshkkumar/VTUResults/
Author: Mahesh Kumar
Author-email: maheshk2194@gmail.com
License: GNU General Public License (GPL)
Platform: UNKNOWN
Classifier: Development Status :: 4 - Beta
Classifier: License :: OSI Approved :: GNU General Public License (GPL)
Classifier: Operating System :: POSIX
Classifier: Intended Audience :: Developers
Classifier: Natural Language :: English
Classifier: Programming Language :: Python
Classifier: Programming Language :: Python :: 2
Classifier: Programming Language :: Python :: 2.7
Classifier: Topic :: Internet
Classifier: Topic :: Internet :: WWW/HTTP :: Browsers
Classifier: Topic :: Internet :: WWW/HTTP :: Indexing/Search
Classifier: Topic :: Software Development :: Libraries
Classifier: Topic :: Software Development :: Libraries :: Python Modules
Classifier: Topic :: Utilities
Requires-Dist: requests (>=2.6.0)
Requires-Dist: BeautifulSoup4 (>=4.3.1)
